<?xml version="1.0" encoding="UTF-8" standalone="yes"?><mtTask><id>000QEU0Z000000000005</id><orgId>000QEU</orgId><name>aaf</name><description></description><createTime>2015-09-17T16:07:00.000Z</createTime><updateTime>2015-10-05T10:10:31.000Z</updateTime><createdBy>uashok@cspi.com</createdBy><updatedBy>uashok@cspi.com</updatedBy><agentId>000QEU08000000000002</agentId><runtimeEnvironmentId>000QEU25000000000002</runtimeEnvironmentId><maxLogs>10</maxLogs><parameters><parameter><id>913992</id><name>$NewSource$</name><type>EXTENDED_SOURCE</type><label>NewSource</label><uiProperties><entry><key>connectionParameterized</key><value>false</value></entry><entry><key>isMsrcFilterParameterized</key><value>false</value></entry><entry><key>isMsrcSortParameterized</key><value>false</value></entry><entry><key>objectParameterized</key><value>false</value></entry><entry><key>visible</key><value>false</value></entry></uiProperties><sourceConnectionId>000QEU0B000000000002</sourceConnectionId><newFlatFile>false</newFlatFile><newObject>false</newObject><showBusinessNames>false</showBusinessNames><naturalOrder>true</naturalOrder><truncateTarget>false</truncateTarget><bulkApiDBTarget>false</bulkApiDBTarget><customFuncCfg><id>-1</id></customFuncCfg><tgtFieldRefs/><extendedObject><object><name>Attachment</name><label>Attachment</label><metadataUpdated>false</metadataUpdated><relations/><children/></object><filters/><sortFields/></extendedObject><runtimeAttrs/><isRESTModernSource>true</isRESTModernSource><isFileList>false</isFileList><handleSpecialChars>false</handleSpecialChars><frsAsset>false</frsAsset><dynamicFileName>false</dynamicFileName><overriddenFields/><fetchMode>ORIGINAL</fetchMode><tgtObjectAttributes/><runtimeParameterData><isConnectionRuntimeParameter>false</isConnectionRuntimeParameter><isObjectRuntimeParameter>false</isObjectRuntimeParameter></runtimeParameterData></parameter><parameter><id>913993</id><name>$NewTarget$</name><type>TARGET</type><label>NewTarget</label><uiProperties><entry><key>connectionParameterized</key><value>false</value></entry><entry><key>objectParameterized</key><value>false</value></entry><entry><key>visible</key><value>false</value></entry><entry><key>defaultTargetUpdateColumns</key><value></value></entry></uiProperties><targetConnectionId>000QEU0B000000000003</targetConnectionId><targetObject>myattach</targetObject><targetObjectLabel>myattach</targetObjectLabel><newFlatFile>false</newFlatFile><newObject>true</newObject><showBusinessNames>false</showBusinessNames><naturalOrder>true</naturalOrder><newObjectName>myattach</newObjectName><truncateTarget>false</truncateTarget><bulkApiDBTarget>false</bulkApiDBTarget><operationType>Insert</operationType><tgtFFAttrs><delimiter>,</delimiter><escapeChar></escapeChar><headerLineNo>1</headerLineNo><id>94086</id><textQualifier>&quot;</textQualifier></tgtFFAttrs><customFuncCfg><id>-1</id></customFuncCfg><tgtFieldRefs/><extendedObject><filters/><sortFields/></extendedObject><runtimeAttrs/><isRESTModernSource>true</isRESTModernSource><isFileList>false</isFileList><handleSpecialChars>false</handleSpecialChars><frsAsset>false</frsAsset><dynamicFileName>false</dynamicFileName><overriddenFields/><fetchMode>ORIGINAL</fetchMode><tgtObjectAttributes/><runtimeParameterData><isConnectionRuntimeParameter>false</isConnectionRuntimeParameter><isObjectRuntimeParameter>false</isObjectRuntimeParameter></runtimeParameterData></parameter></parameters><verbose>false</verbose><mappingId>000QEU17000000000008</mappingId><shortDescription></shortDescription><sessionProperties/><sequences/><inOutParameters/><enableCrossSchemaPushdown>false</enableCrossSchemaPushdown><autoTunedApplied>false</autoTunedApplied><connRuntimeAttrs/></mtTask>