<?xml version="1.0" encoding="UTF-8" standalone="yes"?><connection><id>00175M0B000000000026</id><orgId>00175M</orgId><name>VC_SAP_TABLE_2</name><createTime>2017-05-03T09:10:49.000Z</createTime><updateTime>2017-05-03T09:12:28.000Z</updateTime><createdBy>vcsum@informatica.com</createdBy><updatedBy>vcsum@informatica.com</updatedBy><agentId>00175M0800000000000A</agentId><runtimeEnvironmentId>00175M2500000000000A</runtimeEnvironmentId><instanceName>SAPTableConnector</instanceName><instanceDisplayName>SAPTableConnector</instanceDisplayName><codepage>UTF-8</codepage><type>TOOLKIT</type><port>0</port><password>********</password><majorUpdateTime>2018-05-07T13:31:36.000Z</majorUpdateTime><timeout>60</timeout><connParams><entry><key>Destination</key><value>ge6</value></entry><entry><key>Test Streaming</key><value>false</value></entry><entry><key>agentId</key><value>00175M0800000000000A</value></entry><entry><key>Keystore Location</key></entry><entry><key>agentGroupId</key><value>00175M2500000000000A</value></entry><entry><key>Keystore Password</key></entry><entry><key>Private Key Password</key></entry><entry><key>Https Connection</key><value>false</value></entry><entry><key>orgId</key><value>00175M</value></entry><entry><key>mode</key><value>UPDATE</value></entry><entry><key>Language</key><value>EN</value></entry><entry><key>Username</key><value>PCSTREAM</value></entry><entry><key>Port Range</key></entry><entry><key>Client</key><value>800</value></entry><entry><key>Saprfc Ini Path</key><value>C:\Program Files\Informatica Cloud Secure Agent\apps\Data_Integration_Server\ext\deploy_to_main\bin\rdtm</value></entry><entry><key>Password</key><value>********</value></entry></connParams><internal>false</internal><federatedId>9yTqvduh7EBlqtSu0fLqoq</federatedId><retryNetworkError>false</retryNetworkError></connection>